patatmo/__init__.py
patatmo/api/__init__.py
patatmo/api/authentication.py
patatmo/api/client.py
patatmo/api/errors.py
patatmo/api/requests.py
patatmo/api/responsetypes.py
patatmo/api/variables.py
patatmo/cli/__init__.py
patatmo/utils.py
patatmo-0.2.16.dist-info/LICENSE
patatmo-0.2.16.dist-info/METADATA
patatmo-0.2.16.dist-info/WHEEL
patatmo-0.2.16.dist-info/RECORD
