Metadata-Version: 2.1
Name: patatmo
Version: 0.2.16
Summary: painless access to the netatmo weather api
License: GPLv3
Author: Yann Büchau
Author-email: nobodyinperson@posteo.de
Requires-Python: >=3.9,<4.0
Classifier: License :: Other/Proprietary License
Classifier: Programming Language :: Python :: 3
Classifier: Programming Language :: Python :: 3.9
Classifier: Programming Language :: Python :: 3.10
Classifier: Programming Language :: Python :: 3.11
Classifier: Programming Language :: Python :: 3.12
Requires-Dist: numpy (>=1)
Requires-Dist: pandas (>=1)
